{"GlobalPropertiesHash":"8r1BWOEFK2C6WVCm9kgl+CfrCebZqtfA1KQcy7W4zfA=","FingerprintPatternsHash":"gq3WsqcKBUGTSNle7RKKyXRIwh7M8ccEqOqYvIzoM04=","PropertyOverridesHash":"8ZRc1sGeVrPBx4lD717BgRaQekyh78QKV9SKsdt638U=","InputHashes":["37y0SXowmk4Rcfg9vOwFNrsjk0K56p1NndXhfalKiak=","xD6cenmz\u002BgHGvLLEfbbeYaQ9qD2Bpxg77/TyqP5CKV4=","jdB4S3I8u3jNbHck4ZD5ZS15aFcbpG6nczr9lZVlAH0=","M\u002Bs8XG8ZSufqHUcD2VcTFqpvbvkzj4vK5VGi7M99rHA=","lDjW4d1i15KyjGI74HS9iEy4y7LdekwrLPAw5dHY4jc=","S6fNDT3fz99nLCvduwNGB\u002BIunWL7ovJCEqq7WUHt8Ss=","\u002BtmDZZebDvkOzPvxEKsERK92ScJ1dtqd8giVAMnh3uk=","WW3iPQHx2elvJIZXx0s9lcEuETRNjh2AjIK1HS6EXuU=","3MAB2f2D3orbaCPOq6LW/lmDcpLApJftzPfzTKE/yuM=","fDOGbm1m\u002BCq76crydczS20HdMEaBhb6dNlDlW5L12Wo=","7hTpqIVDLlkv/vzHxveF39W8XtXXaj3QMXBlK\u002BTKF5E=","EH2cV0MtcaiIW2\u002BADfQRQZxlmzWOLUv78FpA/fKSuV0=","4eIZcJtpg0uKdJRmfmfOI8FnD77469tzTv1CujJ3Mn4=","qfQxo9Szm1Lb4i1ndkvL0Gk3xDcv5AIAd5dNrbU1ooo=","ORHeQvbGgId8Imtp4OKqDaKiZZXjqhjxk/bcdA46IkQ="],"CachedAssets":{"37y0SXowmk4Rcfg9vOwFNrsjk0K56p1NndXhfalKiak=":{"Identity":"D:\\backend\\API\\ECommerce.WebSolution\\ECommerce.Web\\wwwroot\\images\\products\\CheesyVegetableLasagna.png","SourceId":"ECommerce.Web","SourceType":"Discovered","ContentRoot":"D:\\backend\\API\\ECommerce.WebSolution\\ECommerce.Web\\wwwroot\\","BasePath":"_content/ECommerce.Web","RelativePath":"images/products/CheesyVegetableLasagna#[.{fingerprint}]?.png","AssetKind":"All","AssetMode":"All","AssetRole":"Primary","AssetMergeBehavior":null,"AssetMergeSource":"","RelatedAsset":null,"AssetTraitName":null,"AssetTraitValue":null,"Fingerprint":"277d94tvkp","Integrity":"UtF\u002BW7wyFOzO0VQ/\u002Bviac9wHc8AQFnmrfraDj9aCUck=","CopyToOutputDirectory":"Never","CopyToPublishDirectory":"PreserveNewest","OriginalItemSpec":"wwwroot\\images\\products\\CheesyVegetableLasagna.png","FileLength":230079,"LastWriteTime":"2025-04-13T13:26:44+00:00"},"xD6cenmz\u002BgHGvLLEfbbeYaQ9qD2Bpxg77/TyqP5CKV4=":{"Identity":"D:\\backend\\API\\ECommerce.WebSolution\\ECommerce.Web\\wwwroot\\images\\products\\ChickenMarsala.png","SourceId":"ECommerce.Web","SourceType":"Discovered","ContentRoot":"D:\\backend\\API\\ECommerce.WebSolution\\ECommerce.Web\\wwwroot\\","BasePath":"_content/ECommerce.Web","RelativePath":"images/products/ChickenMarsala#[.{fingerprint}]?.png","AssetKind":"All","AssetMode":"All","AssetRole":"Primary","AssetMergeBehavior":null,"AssetMergeSource":"","RelatedAsset":null,"AssetTraitName":null,"AssetTraitValue":null,"Fingerprint":"j9gf2gpbng","Integrity":"F9LEXckLS5A1J9CnKJlnvPPXTo4YzrJegjwl4ZRIBl8=","CopyToOutputDirectory":"Never","CopyToPublishDirectory":"PreserveNewest","OriginalItemSpec":"wwwroot\\images\\products\\ChickenMarsala.png","FileLength":75964,"LastWriteTime":"2025-04-13T13:26:44+00:00"},"jdB4S3I8u3jNbHck4ZD5ZS15aFcbpG6nczr9lZVlAH0=":{"Identity":"D:\\backend\\API\\ECommerce.WebSolution\\ECommerce.Web\\wwwroot\\images\\products\\ChickenTeriyakiNoodles.png","SourceId":"ECommerce.Web","SourceType":"Discovered","ContentRoot":"D:\\backend\\API\\ECommerce.WebSolution\\ECommerce.Web\\wwwroot\\","BasePath":"_content/ECommerce.Web","RelativePath":"images/products/ChickenTeriyakiNoodles#[.{fingerprint}]?.png","AssetKind":"All","AssetMode":"All","AssetRole":"Primary","AssetMergeBehavior":null,"AssetMergeSource":"","RelatedAsset":null,"AssetTraitName":null,"AssetTraitValue":null,"Fingerprint":"1r1eq4pg3a","Integrity":"o4WJ\u002Bibl/WfaGi6lgorsjEKBGVosfRdCJ\u002BJXq\u002BxGD48=","CopyToOutputDirectory":"Never","CopyToPublishDirectory":"PreserveNewest","OriginalItemSpec":"wwwroot\\images\\products\\ChickenTeriyakiNoodles.png","FileLength":51969,"LastWriteTime":"2025-04-13T13:26:42+00:00"},"M\u002Bs8XG8ZSufqHUcD2VcTFqpvbvkzj4vK5VGi7M99rHA=":{"Identity":"D:\\backend\\API\\ECommerce.WebSolution\\ECommerce.Web\\wwwroot\\images\\products\\ChickenTikkaMasala.jpg","SourceId":"ECommerce.Web","SourceType":"Discovered","ContentRoot":"D:\\backend\\API\\ECommerce.WebSolution\\ECommerce.Web\\wwwroot\\","BasePath":"_content/ECommerce.Web","RelativePath":"images/products/ChickenTikkaMasala#[.{fingerprint}]?.jpg","AssetKind":"All","AssetMode":"All","AssetRole":"Primary","AssetMergeBehavior":null,"AssetMergeSource":"","RelatedAsset":null,"AssetTraitName":null,"AssetTraitValue":null,"Fingerprint":"xurfn7rtfc","Integrity":"N\u002BIptZASATOvb0xx9LwELSoGChn8OpiNzrrLIi4EXfs=","CopyToOutputDirectory":"Never","CopyToPublishDirectory":"PreserveNewest","OriginalItemSpec":"wwwroot\\images\\products\\ChickenTikkaMasala.jpg","FileLength":139657,"LastWriteTime":"2025-04-13T13:26:42+00:00"},"lDjW4d1i15KyjGI74HS9iEy4y7LdekwrLPAw5dHY4jc=":{"Identity":"D:\\backend\\API\\ECommerce.WebSolution\\ECommerce.Web\\wwwroot\\images\\products\\Congee.png","SourceId":"ECommerce.Web","SourceType":"Discovered","ContentRoot":"D:\\backend\\API\\ECommerce.WebSolution\\ECommerce.Web\\wwwroot\\","BasePath":"_content/ECommerce.Web","RelativePath":"images/products/Congee#[.{fingerprint}]?.png","AssetKind":"All","AssetMode":"All","AssetRole":"Primary","AssetMergeBehavior":null,"AssetMergeSource":"","RelatedAsset":null,"AssetTraitName":null,"AssetTraitValue":null,"Fingerprint":"6obkfgjvl3","Integrity":"6uitpnC1BLi2rjJ/5GpO0E8irqfTFiOCDzKPLIuUuhk=","CopyToOutputDirectory":"Never","CopyToPublishDirectory":"PreserveNewest","OriginalItemSpec":"wwwroot\\images\\products\\Congee.png","FileLength":29716,"LastWriteTime":"2025-04-13T13:26:42+00:00"},"S6fNDT3fz99nLCvduwNGB\u002BIunWL7ovJCEqq7WUHt8Ss=":{"Identity":"D:\\backend\\API\\ECommerce.WebSolution\\ECommerce.Web\\wwwroot\\images\\products\\CreamyGochujangTortellini.png","SourceId":"ECommerce.Web","SourceType":"Discovered","ContentRoot":"D:\\backend\\API\\ECommerce.WebSolution\\ECommerce.Web\\wwwroot\\","BasePath":"_content/ECommerce.Web","RelativePath":"images/products/CreamyGochujangTortellini#[.{fingerprint}]?.png","AssetKind":"All","AssetMode":"All","AssetRole":"Primary","AssetMergeBehavior":null,"AssetMergeSource":"","RelatedAsset":null,"AssetTraitName":null,"AssetTraitValue":null,"Fingerprint":"m6v6958kfh","Integrity":"XkAp89ZW560xZlvEhuxFO3mt7qa3toZ2AK/oa1XxnwU=","CopyToOutputDirectory":"Never","CopyToPublishDirectory":"PreserveNewest","OriginalItemSpec":"wwwroot\\images\\products\\CreamyGochujangTortellini.png","FileLength":520185,"LastWriteTime":"2025-04-13T13:26:42+00:00"},"\u002BtmDZZebDvkOzPvxEKsERK92ScJ1dtqd8giVAMnh3uk=":{"Identity":"D:\\backend\\API\\ECommerce.WebSolution\\ECommerce.Web\\wwwroot\\images\\products\\CrispyVegetablePakoras.png","SourceId":"ECommerce.Web","SourceType":"Discovered","ContentRoot":"D:\\backend\\API\\ECommerce.WebSolution\\ECommerce.Web\\wwwroot\\","BasePath":"_content/ECommerce.Web","RelativePath":"images/products/CrispyVegetablePakoras#[.{fingerprint}]?.png","AssetKind":"All","AssetMode":"All","AssetRole":"Primary","AssetMergeBehavior":null,"AssetMergeSource":"","RelatedAsset":null,"AssetTraitName":null,"AssetTraitValue":null,"Fingerprint":"orbj85bm9q","Integrity":"VC5AjwmbqRt68fQsihf1EuSDAviUzshjN\u002BUhy1m\u002BKo8=","CopyToOutputDirectory":"Never","CopyToPublishDirectory":"PreserveNewest","OriginalItemSpec":"wwwroot\\images\\products\\CrispyVegetablePakoras.png","FileLength":61748,"LastWriteTime":"2025-04-13T13:26:42+00:00"},"WW3iPQHx2elvJIZXx0s9lcEuETRNjh2AjIK1HS6EXuU=":{"Identity":"D:\\backend\\API\\ECommerce.WebSolution\\ECommerce.Web\\wwwroot\\images\\products\\HaluskiNoodles.png","SourceId":"ECommerce.Web","SourceType":"Discovered","ContentRoot":"D:\\backend\\API\\ECommerce.WebSolution\\ECommerce.Web\\wwwroot\\","BasePath":"_content/ECommerce.Web","RelativePath":"images/products/HaluskiNoodles#[.{fingerprint}]?.png","AssetKind":"All","AssetMode":"All","AssetRole":"Primary","AssetMergeBehavior":null,"AssetMergeSource":"","RelatedAsset":null,"AssetTraitName":null,"AssetTraitValue":null,"Fingerprint":"5p0dqi4iia","Integrity":"NxmWPQ156cjX4jYqmChMpoI\u002BOL5r\u002B8RGO4vWNp7GJdA=","CopyToOutputDirectory":"Never","CopyToPublishDirectory":"PreserveNewest","OriginalItemSpec":"wwwroot\\images\\products\\HaluskiNoodles.png","FileLength":1050666,"LastWriteTime":"2025-04-13T13:26:42+00:00"},"3MAB2f2D3orbaCPOq6LW/lmDcpLApJftzPfzTKE/yuM=":{"Identity":"D:\\backend\\API\\ECommerce.WebSolution\\ECommerce.Web\\wwwroot\\images\\products\\PepperPasta.png","SourceId":"ECommerce.Web","SourceType":"Discovered","ContentRoot":"D:\\backend\\API\\ECommerce.WebSolution\\ECommerce.Web\\wwwroot\\","BasePath":"_content/ECommerce.Web","RelativePath":"images/products/PepperPasta#[.{fingerprint}]?.png","AssetKind":"All","AssetMode":"All","AssetRole":"Primary","AssetMergeBehavior":null,"AssetMergeSource":"","RelatedAsset":null,"AssetTraitName":null,"AssetTraitValue":null,"Fingerprint":"kg3z3o7bg8","Integrity":"RG9bbXhD6PAdvoY7drWGt30Ht/5lo5cFatFguZRdm7A=","CopyToOutputDirectory":"Never","CopyToPublishDirectory":"PreserveNewest","OriginalItemSpec":"wwwroot\\images\\products\\PepperPasta.png","FileLength":854706,"LastWriteTime":"2025-04-13T13:26:44+00:00"},"fDOGbm1m\u002BCq76crydczS20HdMEaBhb6dNlDlW5L12Wo=":{"Identity":"D:\\backend\\API\\ECommerce.WebSolution\\ECommerce.Web\\wwwroot\\images\\products\\ShrimpEggFooYoung.png","SourceId":"ECommerce.Web","SourceType":"Discovered","ContentRoot":"D:\\backend\\API\\ECommerce.WebSolution\\ECommerce.Web\\wwwroot\\","BasePath":"_content/ECommerce.Web","RelativePath":"images/products/ShrimpEggFooYoung#[.{fingerprint}]?.png","AssetKind":"All","AssetMode":"All","AssetRole":"Primary","AssetMergeBehavior":null,"AssetMergeSource":"","RelatedAsset":null,"AssetTraitName":null,"AssetTraitValue":null,"Fingerprint":"msr8fm8kz0","Integrity":"tkWJ8RVcg7ciRVqma5m4EG2qbpof108mIsr1CKaWhHA=","CopyToOutputDirectory":"Never","CopyToPublishDirectory":"PreserveNewest","OriginalItemSpec":"wwwroot\\images\\products\\ShrimpEggFooYoung.png","FileLength":83807,"LastWriteTime":"2025-04-13T13:26:42+00:00"},"7hTpqIVDLlkv/vzHxveF39W8XtXXaj3QMXBlK\u002BTKF5E=":{"Identity":"D:\\backend\\API\\ECommerce.WebSolution\\ECommerce.Web\\wwwroot\\images\\products\\TandooriChicken.png","SourceId":"ECommerce.Web","SourceType":"Discovered","ContentRoot":"D:\\backend\\API\\ECommerce.WebSolution\\ECommerce.Web\\wwwroot\\","BasePath":"_content/ECommerce.Web","RelativePath":"images/products/TandooriChicken#[.{fingerprint}]?.png","AssetKind":"All","AssetMode":"All","AssetRole":"Primary","AssetMergeBehavior":null,"AssetMergeSource":"","RelatedAsset":null,"AssetTraitName":null,"AssetTraitValue":null,"Fingerprint":"0akmarr0bz","Integrity":"KFY9bmxC6u86Ivyff764oENxtDKR0DNw8UNJRuj3iog=","CopyToOutputDirectory":"Never","CopyToPublishDirectory":"PreserveNewest","OriginalItemSpec":"wwwroot\\images\\products\\TandooriChicken.png","FileLength":508720,"LastWriteTime":"2025-04-13T13:26:44+00:00"},"EH2cV0MtcaiIW2\u002BADfQRQZxlmzWOLUv78FpA/fKSuV0=":{"Identity":"D:\\backend\\API\\ECommerce.WebSolution\\ECommerce.Web\\wwwroot\\images\\products\\VegetarianKorma.png","SourceId":"ECommerce.Web","SourceType":"Discovered","ContentRoot":"D:\\backend\\API\\ECommerce.WebSolution\\ECommerce.Web\\wwwroot\\","BasePath":"_content/ECommerce.Web","RelativePath":"images/products/VegetarianKorma#[.{fingerprint}]?.png","AssetKind":"All","AssetMode":"All","AssetRole":"Primary","AssetMergeBehavior":null,"AssetMergeSource":"","RelatedAsset":null,"AssetTraitName":null,"AssetTraitValue":null,"Fingerprint":"7n9bvio4t8","Integrity":"k4whsXR6\u002BIYDgIN67hrYyg8AXzEiqiFW5wveZ8\u002BGvgA=","CopyToOutputDirectory":"Never","CopyToPublishDirectory":"PreserveNewest","OriginalItemSpec":"wwwroot\\images\\products\\VegetarianKorma.png","FileLength":1192584,"LastWriteTime":"2025-04-13T13:26:42+00:00"},"4eIZcJtpg0uKdJRmfmfOI8FnD77469tzTv1CujJ3Mn4=":{"Identity":"D:\\backend\\API\\ECommerce.WebSolution\\ECommerce.Web\\wwwroot\\images\\products\\VegetarianRefriedBeans.png","SourceId":"ECommerce.Web","SourceType":"Discovered","ContentRoot":"D:\\backend\\API\\ECommerce.WebSolution\\ECommerce.Web\\wwwroot\\","BasePath":"_content/ECommerce.Web","RelativePath":"images/products/VegetarianRefriedBeans#[.{fingerprint}]?.png","AssetKind":"All","AssetMode":"All","AssetRole":"Primary","AssetMergeBehavior":null,"AssetMergeSource":"","RelatedAsset":null,"AssetTraitName":null,"AssetTraitValue":null,"Fingerprint":"uazi5tssqj","Integrity":"NvycooL3DfYDM2KgXQPAxSdCOokaiLpXnAnDykystws=","CopyToOutputDirectory":"Never","CopyToPublishDirectory":"PreserveNewest","OriginalItemSpec":"wwwroot\\images\\products\\VegetarianRefriedBeans.png","FileLength":169136,"LastWriteTime":"2025-04-13T13:26:42+00:00"}},"CachedCopyCandidates":{}}